Metadata-Version: 2.0
Name: sapphire
Version: 1.0.2
Summary: Sapphire Tools
Home-page: UNKNOWN
Author: UNKNOWN
Author-email: UNKNOWN
License: GNU General Public License v3
Platform: UNKNOWN
Requires-Dist: appdirs (==1.4.3)
Requires-Dist: bitstring (==3.1.5)
Requires-Dist: catbus
Requires-Dist: click (>=6.6)
Requires-Dist: cmd2 (==0.6.9)
Requires-Dist: crcmod (==1.7)
Requires-Dist: elysianfields (>=1.0)
Requires-Dist: fnvhash
Requires-Dist: intelhex (==2.1)
Requires-Dist: pydispatcher (==2.0.5)
Requires-Dist: pyparsing (==2.2.0)
Requires-Dist: pyserial (==3.2.1)
Requires-Dist: requests (==2.18.4)
Requires-Dist: setuptools (==34.2.0)
